nbmachine/__init__.py
nbmachine/modular.py
nbmachine-0.0.7.dist-info/LICENSE
nbmachine-0.0.7.dist-info/METADATA
nbmachine-0.0.7.dist-info/WHEEL
nbmachine-0.0.7.dist-info/top_level.txt
nbmachine-0.0.7.dist-info/RECORD
