Metadata-Version: 2.1
Name: nbmachine
Version: 0.0.7
Summary: Notebook Machine
Home-page: https://github.com/pypa/sampleproject
Author: Dave Killough
Author-email: Dave Killough <dave.killough@gmail.com>
Project-URL: Homepage, https://github.com/pypa/sampleproject
Project-URL: Bug Tracker, https://github.com/pypa/sampleproject/issues
Classifier: Programming Language :: Python :: 3
Classifier: License :: OSI Approved :: MIT License
Classifier: Operating System :: OS Independent
Requires-Python: >=3.7
License-File: LICENSE
Requires-Dist: ipynb (>=0.5.1)
